fw_gear_dicom_send/__init__.py
fw_gear_dicom_send/dicom.py
fw_gear_dicom_send/main.py
fw_gear_dicom_send/parser.py
fw_gear_dicom_send/reporter.py
fw_gear_dicom_send/sender.py
fw_gear_dicom_send-4.2.0.dist-info/LICENSE
fw_gear_dicom_send-4.2.0.dist-info/METADATA
fw_gear_dicom_send-4.2.0.dist-info/WHEEL
fw_gear_dicom_send-4.2.0.dist-info/RECORD
